pynoesmartmeter/__init__.py
pynoesmartmeter/client.py
pynoesmartmeter/errors.py
pynoesmartmeter-0.3.5.dist-info/LICENSE
pynoesmartmeter-0.3.5.dist-info/METADATA
pynoesmartmeter-0.3.5.dist-info/WHEEL
pynoesmartmeter-0.3.5.dist-info/RECORD
