Metadata-Version: 2.1
Name: pynoesmartmeter
Version: 0.3.5
Summary: Python library to access the Netz Nö (EVN) Smart Meter private API
License: MIT
Author: David Illichmann
Author-email: david.illichmann@ebcont.com
Requires-Python: >=3.11,<4.0
Classifier: License :: OSI Approved :: MIT License
Classifier: Programming Language :: Python :: 3
Classifier: Programming Language :: Python :: 3.11
Classifier: Programming Language :: Python :: 3.12
Requires-Dist: aiofiles (>=23.2.1,<24.0.0)
Requires-Dist: asyncio (>=3.4.3,<4.0.0)
Requires-Dist: httpx (>=0.27.0,<0.28.0)
Requires-Dist: requests (>=2.31.0,<3.0.0)
